guantlet/__init__.py
guantlet/main.py
gauntlet-0.1.0.dist-info/METADATA
gauntlet-0.1.0.dist-info/WHEEL
gauntlet-0.1.0.dist-info/entry_points.txt
gauntlet-0.1.0.dist-info/top_level.txt
gauntlet-0.1.0.dist-info/RECORD
